{
    "today": "2025-08-24",
    "future_date": "2025-08-27",
    "projects": [
        {
            "kbDate": "2025-08-25",
            "prjName": "宁波市水务环境集团2025年第三方环境检测服务项目（重招）",
            "bulletinId": "65960a5e-a8ab-4d28-aec4-892251fc3914",
            "prjType": "信息化服务类项目"
        },
        {
            "kbDate": "2025-08-25",
            "prjName": "海欣控股集团年度技术顾问服务",
            "bulletinId": "adabfd2a-9423-4cd8-9b13-63ea26b11623",
            "prjType": "信息化服务类项目"
        },
        {
            "kbDate": "2025-08-25",
            "prjName": "宁波市海曙区蓝天路（藕缆桥河—迎春路） 道路工程（施工、监理）招标代理服务",
            "bulletinId": "a51dc7ef-81b4-4e8e-a910-579f51c9e96b",
            "prjType": "工程类项目"
        },
        {
            "kbDate": "2025-08-25",
            "prjName": "在管公共停车场消防设施设备维修工程",
            "bulletinId": "4c8eaaf4-147e-4861-b93f-a8e69cea5599",
            "prjType": "工程类项目"
        },
        {
            "kbDate": "2025-08-25",
            "prjName": "江北区JB16-02-3、JB16-02-4a地块项目景观家具采购及相关服务",
            "bulletinId": "24738ef7-d16f-4893-bad1-c36644dee56c",
            "prjType": "工程类项目"
        },
        {
            "kbDate": "2025-08-25",
            "prjName": "慈城古县城机器人智慧化服务采购",
            "bulletinId": "6693ce72-6da3-4030-87ff-d1488bd5787c",
            "prjType": "信息化服务类项目"
        },
        {
            "kbDate": "2025-08-25",
            "prjName": "清林闲庭地块新建学校工程项目2x1600KVA专变工程采购",
            "bulletinId": "0d9c7d86-4f37-4ef0-aaa3-6d19d6dc94c1",
            "prjType": "工程类项目"
        },
        {
            "kbDate": "2025-08-25",
            "prjName": "清林闲庭地块新建菜场项目2X1000KVA专变工程设备采购",
            "bulletinId": "cc7580b4-044e-4659-9369-1614ee26f14e",
            "prjType": "工程类项目"
        },
        {
            "kbDate": "2025-08-25",
            "prjName": "宁波工业供水有限公司4000kVA箱变（10kV/6kV）临时租赁项目",
            "bulletinId": "955cefd9-4577-4bca-9c88-7f73ce84abac",
            "prjType": "信息化服务类项目"
        },
        {
            "kbDate": "2025-08-25",
            "prjName": "慈城古县城中华路南侧草坪营地",
            "bulletinId": "049e0254-10f2-4746-80cd-fdbcab2da01e",
            "prjType": "工程类项目"
        },
        {
            "kbDate": "2025-08-25",
            "prjName": "宁波大榭开发区黎明物业管理有限公司生活垃圾桶边督导项目",
            "bulletinId": "0f99cf35-4fd5-461d-ab12-814dd89ea209",
            "prjType": "其他项目"
        },
        {
            "kbDate": "2025-08-25",
            "prjName": "黎明物业管理有限公司海文花园东、西区保洁及垃圾分类桶边督导服务外包项目",
            "bulletinId": "2395811b-9584-4451-a986-76e99d99dc42",
            "prjType": "其他项目"
        },
        {
            "kbDate": "2025-08-25",
            "prjName": "北仑区社会治安动态视频监控系统链路改造项目",
            "bulletinId": "eb58e0d8-3d00-4275-892f-46e4f7dd995e",
            "prjType": "工程类项目"
        },
        {
            "kbDate": "2025-08-25",
            "prjName": "宁波市总工会共富工坊平台运营合作项目",
            "bulletinId": "5d27f286-9964-456d-b648-35aeff6db236",
            "prjType": "信息化服务类项目"
        },
        {
            "kbDate": "2025-08-25",
            "prjName": "环城南路东延快速路一期工程（邱隘立交段）等项目施工期防洪评价",
            "bulletinId": "7b5aab61-6aa6-4ce6-a35f-222d15dafc39",
            "prjType": "工程类项目"
        },
        {
            "kbDate": "2025-08-25",
            "prjName": "物产中大城投（宁波）控股有限公司2025-2027年度多联机空调机组集中采购项目",
            "bulletinId": "0cd642c1-6ed0-45a0-b78d-670eb3256d38",
            "prjType": "信息化软硬件采购类项目"
        },
        {
            "kbDate": "2025-08-25",
            "prjName": "宁波市城庄路北延（宁慈路-荣吉西路）工程（涉铁段）试验检测、桩基检测项目",
            "bulletinId": "d282af03-d9b1-4d62-a8de-6d09abe99410",
            "prjType": "工程类项目"
        },
        {
            "kbDate": "2025-08-25",
            "prjName": "和义大道购物中心街区更新项目VIP LOUNGE软装采购项目",
            "bulletinId": "a0527714-fd1f-467e-a3b8-38efc8db9cf2",
            "prjType": "工程类项目"
        },
        {
            "kbDate": "2025-08-25",
            "prjName": "宁波大榭热电有限公司灰渣处理服务商采购项目（第二次重招）",
            "bulletinId": "96cbde8c-aaac-41be-930d-516e359c6e66",
            "prjType": "信息化服务类项目"
        },
        {
            "kbDate": "2025-08-25",
            "prjName": "宁波市海曙区长春路沿线提升改造工程（施工）招标代理服务",
            "bulletinId": "fc05ee97-175e-48ff-9974-4f3672ff7ed6",
            "prjType": "工程类项目"
        },
        {
            "kbDate": "2025-08-25",
            "prjName": "宁波高新区未来产业创新园(一期)人才公寓南区通讯工程",
            "bulletinId": "47fac439-7382-4500-a192-052391627aac",
            "prjType": "工程类项目"
        },
        {
            "kbDate": "2025-08-25",
            "prjName": "宁波市水务环境集团2025年二次供水泵房不锈钢立式多级离心泵采购项目",
            "bulletinId": "9ad20992-52d4-4a37-85a1-5f626bf8c324",
            "prjType": "信息化软硬件采购类项目"
        },
        {
            "kbDate": "2025-08-25",
            "prjName": "城投集团总部食堂采购服务项目",
            "bulletinId": "b21833b9-767d-4499-9570-0c460b16f4af",
            "prjType": "信息化服务类项目"
        },
        {
            "kbDate": "2025-08-25",
            "prjName": "慈溪东部引水工程海域相关论证项目",
            "bulletinId": "9145f3e0-4243-4922-a6db-c0d9c121dec8",
            "prjType": "工程类项目"
        },
        {
            "kbDate": "2025-08-25",
            "prjName": "卫生设施信息化服务采购项目",
            "bulletinId": "c8818a8b-3fb2-4eeb-b052-6b9b75e021b8",
            "prjType": "信息化服务类项目"
        },
        {
            "kbDate": "2025-08-25",
            "prjName": "慈城镇城东五村联建房项目基础设施配套工程（勘察设计）",
            "bulletinId": "948ea3f6-d6a9-4ef4-b14d-1a11f04ebc39",
            "prjType": "工程类项目"
        },
        {
            "kbDate": "2025-08-25",
            "prjName": "宁波市水务环境集团2025年工程公司钢筋、水泥采购项目",
            "bulletinId": "ecec7f28-277b-4bf9-99c8-7fa333d0fd68",
            "prjType": "工程类项目"
        },
        {
            "kbDate": "2025-08-25",
            "prjName": "甬江实验室A区5-4地块项目实体结构及节能检测",
            "bulletinId": "40fb74df-a04d-4881-8551-3ec8f9a8beef",
            "prjType": "工程类项目"
        },
        {
            "kbDate": "2025-08-25",
            "prjName": "保税东一、西二生活区室外加装电梯工程（电梯采购）",
            "bulletinId": "efecf39f-236b-41bb-81d8-8146843c0903",
            "prjType": "工程类项目"
        },
        {
            "kbDate": "2025-08-25",
            "prjName": "宁波大榭热电有限公司发电机涉网试验",
            "bulletinId": "1a6845b1-8e65-4268-b8b5-3f6f0ea32b0e",
            "prjType": "工程类项目"
        },
        {
            "kbDate": "2025-08-25",
            "prjName": "梅山湾生命健康科创园项目（一期）外线电力接入工程设备采购",
            "bulletinId": "9ea8acbb-b97c-4c4a-85a7-6703ddf37031",
            "prjType": "信息化软硬件采购类项目"
        },
        {
            "kbDate": "2025-08-25",
            "prjName": "半边山东海学堂厨房用品采购项目（3次重发）",
            "bulletinId": "c8602deb-ba69-4f36-a288-e930672915f0",
            "prjType": "其他项目"
        },
        {
            "kbDate": "2025-08-25",
            "prjName": "半边山东海学堂客房用品采购项目（3次重发）",
            "bulletinId": "db96e5cb-e965-4987-b230-bd1babf8ce56",
            "prjType": "其他项目"
        },
        {
            "kbDate": "2025-08-25",
            "prjName": "半边山东海学堂研学活动物品采购项目（3次重发）",
            "bulletinId": "f500504f-0583-469e-90d2-307f8f731166",
            "prjType": "其他项目"
        },
        {
            "kbDate": "2025-08-25",
            "prjName": "东海半边山社会道路标识牌新设工程",
            "bulletinId": "87ae96df-c336-40d5-8d34-9bba9fca51e1",
            "prjType": "工程类项目"
        },
        {
            "kbDate": "2025-08-26",
            "prjName": "宁波市海曙区尚书街39号房屋加固改造更新工程（设计）",
            "bulletinId": "607fb452-7d6c-45fb-a946-d78c159346d6",
            "prjType": "工程类项目"
        },
        {
            "kbDate": "2025-08-26",
            "prjName": "姚江水厂35kV高压开关柜深度维保项目",
            "bulletinId": "73c7a145-0134-443b-b5d6-708a81bc9eb4",
            "prjType": "工程类项目"
        },
        {
            "kbDate": "2025-08-26",
            "prjName": "宁波市江北区姚江北岸奥体西侧JB16-06-2b、JB16-06-2c地块土壤污染状况调查项目",
            "bulletinId": "8b326652-27a7-41a5-b531-f4ff4ce9ef19",
            "prjType": "其他项目"
        },
        {
            "kbDate": "2025-08-26",
            "prjName": "桃源水厂膜池空压系统改造工程",
            "bulletinId": "0a37362c-b8cf-4474-8c3c-99c086a9b067",
            "prjType": "工程类项目"
        },
        {
            "kbDate": "2025-08-26",
            "prjName": "地磅维保服务采购项目",
            "bulletinId": "d0c44b27-1c21-4e62-a2af-60d4c0af1ae2",
            "prjType": "信息化服务类项目"
        },
        {
            "kbDate": "2025-08-26",
            "prjName": "宁波市鄞西污水处理厂二期工程10kV供电外线施工设备采购",
            "bulletinId": "b791a24d-4f13-43e9-8670-4fd52e482ab7",
            "prjType": "工程类项目"
        },
        {
            "kbDate": "2025-08-26",
            "prjName": "智序港城车后代办商城服务升级和移动端建设项目",
            "bulletinId": "90acd575-8f8a-4ade-9c2c-c9845ca016c1",
            "prjType": "信息化服务类项目"
        },
        {
            "kbDate": "2025-08-26",
            "prjName": "宁波地铁产业工程有限公司技术咨询服务项目",
            "bulletinId": "1e89507c-29c0-44d9-8ea6-07a3ba0c153d",
            "prjType": "信息化服务类项目"
        },
        {
            "kbDate": "2025-08-26",
            "prjName": "宁波通商控股集团有限公司债权投资计划专业管理机构招标项目",
            "bulletinId": "d40b0feb-9f63-42f6-b043-03b3ec58934d",
            "prjType": "其他项目"
        },
        {
            "kbDate": "2025-08-26",
            "prjName": "宁波悦城生活服务有限公司2025年-2027年秩序安保服务外包",
            "bulletinId": "2202d7f9-07b3-40a8-aa4e-d13d10213beb",
            "prjType": "信息化服务类项目"
        },
        {
            "kbDate": "2025-08-26",
            "prjName": "宁波市水务环境集团2025年工程公司商品混凝土采购项目",
            "bulletinId": "b2691853-4161-405d-9cac-5ea7ede6c7db",
            "prjType": "工程类项目"
        },
        {
            "kbDate": "2025-08-26",
            "prjName": "2025年度天童庄员工宿舍一期屋面热水系统改造项目",
            "bulletinId": "2d2f9888-4edf-40a7-9547-c8af4bed7f00",
            "prjType": "工程类项目"
        },
        {
            "kbDate": "2025-08-26",
            "prjName": "智博会开幕主题活动策划执行与综合保障服务",
            "bulletinId": "c29e28c8-9d40-4165-94f5-d2bb2c23aba5",
            "prjType": "信息化服务类项目"
        },
        {
            "kbDate": "2025-08-26",
            "prjName": "鄞州区WX02-07-07地块项目室内环境检测",
            "bulletinId": "f64bc618-71f8-49f4-be5b-2e21edcc68da",
            "prjType": "信息化服务类项目"
        },
        {
            "kbDate": "2025-08-26",
            "prjName": "杭州湾大桥交通基础设施数字化转型升级试点专项工程",
            "bulletinId": "d859c3be-9ce8-486f-8441-b12f753275ff",
            "prjType": "工程类项目"
        },
        {
            "kbDate": "2025-08-26",
            "prjName": "第十五届智慧城市与智能经济博览会搭建服务项目",
            "bulletinId": "55d29193-afbc-4367-b7be-4863f73387cc",
            "prjType": "工程类项目"
        },
        {
            "kbDate": "2025-08-26",
            "prjName": "镇海区庄市规划小学提升改造工程（施工）",
            "bulletinId": "c1ed4408-9c25-482e-844d-d8641483e35a",
            "prjType": "工程类项目"
        },
        {
            "kbDate": "2025-08-26",
            "prjName": "广场公司2025年度景观水体水质日常养护服务采购",
            "bulletinId": "3ead851e-781f-44dc-9338-d9d7ac9df650",
            "prjType": "信息化服务类项目"
        },
        {
            "kbDate": "2025-08-26",
            "prjName": "众创空间给水总管改造工程（2025年度）（工程结算审核）",
            "bulletinId": "6451066c-e5e3-4378-8df2-1f7a8cc2d948",
            "prjType": "工程类项目"
        },
        {
            "kbDate": "2025-08-26",
            "prjName": "钱湖秘境浮桥太阳能乌龟灯采购安装项目",
            "bulletinId": "fc0efa39-e09f-439d-8f77-cb3a34b580e8",
            "prjType": "工程类项目"
        },
        {
            "kbDate": "2025-08-26",
            "prjName": "卡丁车备品备件采购",
            "bulletinId": "78e6c3f7-9249-4e20-a4fc-3b770ce3c434",
            "prjType": "其他项目"
        },
        {
            "kbDate": "2025-08-26",
            "prjName": "南洋小城NY-03-05d项目营销办公室家具采购项目",
            "bulletinId": "e63833ea-6e3c-467f-9b54-adce4be023b9",
            "prjType": "其他项目"
        },
        {
            "kbDate": "2025-08-26",
            "prjName": "杭州湾大桥多智能协同运维系统开发",
            "bulletinId": "b026f193-0f0e-4e9a-8ad0-b7a0856a2b27",
            "prjType": "信息化建设类项目"
        },
        {
            "kbDate": "2025-08-26",
            "prjName": "北仑区新碶街道星阳菜场日常运营管理服务采购项目（重新发布）",
            "bulletinId": "7823b9f7-6fcd-4d60-a014-0b946bb809ec",
            "prjType": "信息化服务类项目"
        },
        {
            "kbDate": "2025-08-26",
            "prjName": "2025年度制水分公司盆景租摆服务采购项目",
            "bulletinId": "fb39e82f-0026-4af3-81c3-7afc948a8196",
            "prjType": "信息化服务类项目"
        },
        {
            "kbDate": "2025-08-26",
            "prjName": "五一广场舞台设施设备提升项目",
            "bulletinId": "ee3f12c2-f35a-437f-a193-295d8a401751",
            "prjType": "工程类项目"
        },
        {
            "kbDate": "2025-08-26",
            "prjName": "宁波高新区市政环境服务有限公司物料粉碎车采购项目",
            "bulletinId": "49d8aa77-5d5d-43c6-86fa-7e2956ec2bc4",
            "prjType": "工程类项目"
        },
        {
            "kbDate": "2025-08-26",
            "prjName": "慈城官山印样板房及售楼招商中心室内设计咨询服务项目（重发）",
            "bulletinId": "8fb35331-bdf9-4418-ac2b-08f04e19c9ab",
            "prjType": "工程类项目"
        },
        {
            "kbDate": "2025-08-26",
            "prjName": "清林闲庭地块新建学校工程项目开关站工程设备采购",
            "bulletinId": "105bc860-7862-4742-b12f-c30d49aeb894",
            "prjType": "工程类项目"
        },
        {
            "kbDate": "2025-08-26",
            "prjName": "宁波工业供水有限公司滤池气冲阀、清水阀执行机构采购项目",
            "bulletinId": "83c135bc-c60c-4fd0-89f1-8321bef746ee",
            "prjType": "信息化软硬件采购类项目"
        },
        {
            "kbDate": "2025-08-26",
            "prjName": "“十五五”发展规划编制服务项目",
            "bulletinId": "cb956167-9a82-4b3e-8b26-11e8ab846c8e",
            "prjType": "信息化服务类项目"
        },
        {
            "kbDate": "2025-08-26",
            "prjName": "破碎机刀轴维修及撕碎机刀片采购更换项目",
            "bulletinId": "31fa2356-8d6a-4db3-a520-413bd5adc55d",
            "prjType": "工程类项目"
        },
        {
            "kbDate": "2025-08-26",
            "prjName": "岩东污水处理厂飞力潜水泵维护保养项目",
            "bulletinId": "b98df585-6e4d-49ce-8f91-2bdf75bae10f",
            "prjType": "工程类项目"
        },
        {
            "kbDate": "2025-08-26",
            "prjName": "宁波市海曙区阳光广场市政工程改造提升项目（施工）招标代理",
            "bulletinId": "c37f0f07-6096-47dc-8761-5920f28ae1cf",
            "prjType": "工程类项目"
        },
        {
            "kbDate": "2025-08-26",
            "prjName": "宁波市海曙区阳光广场市政工程改造提升项目招标控制价编制",
            "bulletinId": "ee356f6c-8f07-4bed-9149-a6ca7ac07fb0",
            "prjType": "工程类项目"
        },
        {
            "kbDate": "2025-08-26",
            "prjName": "宁波市海曙区阳光广场市政工程改造提升项目施工阶段全过程工程造价控制、工程结算审核、财务决算编制",
            "bulletinId": "bb4e9325-fea4-4d77-ba7a-759b4798ab14",
            "prjType": "工程类项目"
        },
        {
            "kbDate": "2025-08-26",
            "prjName": "宁波甬江软件产业园（鄞州信创园）电子设备制造项目试运营期室内装修设计",
            "bulletinId": "6fdda70b-7f5c-43c0-98b7-3bd7684b3fda",
            "prjType": "工程类项目"
        },
        {
            "kbDate": "2025-08-26",
            "prjName": "宁波洪塘220KV变电站旧址周边地块地质灾害风险性评估项目 ",
            "bulletinId": "07654ec3-02d8-475c-88ef-7380752d24a7",
            "prjType": "工程类项目"
        },
        {
            "kbDate": "2025-08-26",
            "prjName": "环岛东路388号厂房维修工程",
            "bulletinId": "3bc7cac9-361d-4ae8-80c5-4db390252547",
            "prjType": "工程类项目"
        },
        {
            "kbDate": "2025-08-26",
            "prjName": "综保区物流中心临时房升级改造项目",
            "bulletinId": "ea6b3277-55f1-4e83-8da6-e07d587251a2",
            "prjType": "工程类项目"
        },
        {
            "kbDate": "2025-08-26",
            "prjName": "宁波天一绿色生态科技有限公司2025-2026年度环境检测部分服务项目招标代理",
            "bulletinId": "74b17d33-adec-4c79-b1fd-e54714401119",
            "prjType": "信息化服务类项目"
        },
        {
            "kbDate": "2025-08-26",
            "prjName": "宁波天一绿色生态科技有限公司2025-2026年度环境检测部分服务项目招标控制价编制",
            "bulletinId": "faaec6a4-3b14-428a-b9e9-6b1e405d8a51",
            "prjType": "信息化服务类项目"
        },
        {
            "kbDate": "2025-08-27",
            "prjName": "绿色生态公司检测业务专用燃油车年度租赁项目",
            "bulletinId": "3a6cc2a8-f416-40b9-af71-0359333f8cfa",
            "prjType": "信息化服务类项目"
        },
        {
            "kbDate": "2025-08-27",
            "prjName": "开投集团生产经营保障用车采购项目",
            "bulletinId": "6a706943-83af-4044-a892-306d99adb568",
            "prjType": "其他项目"
        },
        {
            "kbDate": "2025-08-27",
            "prjName": "宁波大榭开发区自来水有限公司2025年度水表采购项目",
            "bulletinId": "dc59b1d5-9f07-4716-8207-e21cd8297403",
            "prjType": "信息化软硬件采购类项目"
        },
        {
            "kbDate": "2025-08-27",
            "prjName": "宁波地铁产业工程有限公司2025年-2027年知识产权代理项目",
            "bulletinId": "18be5018-ed8d-4d92-80e3-f4206a1da57f",
            "prjType": "信息化服务类项目"
        },
        {
            "kbDate": "2025-08-27",
            "prjName": "鄞州区YZ01-03-05-1、YZ01-03-05-2地块项目营销阵地特装布置",
            "bulletinId": "b863214d-0bc9-47e5-8ce9-88371c2cca50",
            "prjType": "工程类项目"
        },
        {
            "kbDate": "2025-08-27",
            "prjName": "宁波北仑广电网络有限公司材料（电力电缆、光配件、光接收机、分支分配器）采购项目",
            "bulletinId": "86415ad2-c596-42ec-b977-4d18759ebf78",
            "prjType": "信息化软硬件采购类项目"
        },
        {
            "kbDate": "2025-08-27",
            "prjName": "G92杭州湾地区环线高速公路宁波好思房至戚家山段工程基于三维激光扫描的装配式桥梁建造测控技术研究与应用",
            "bulletinId": "e29963e1-a38e-4cf3-871c-643bcb6bfb3e",
            "prjType": "工程类项目"
        },
        {
            "kbDate": "2025-08-27",
            "prjName": "南苑望海酒店客房电器及定制品类采购项目",
            "bulletinId": "87f12a95-e155-4443-abdd-b9797acdb1cb",
            "prjType": "信息化软硬件采购类项目"
        },
        {
            "kbDate": "2025-08-27",
            "prjName": "南苑望海酒店、招宝山饭店电视机采购项目",
            "bulletinId": "d6fca494-b64c-4e10-a842-a401b9578823",
            "prjType": "信息化软硬件采购类项目"
        },
        {
            "kbDate": "2025-08-27",
            "prjName": "宁波市科技高级中学古林校区2025年维修工程窗帘采购及相关服务",
            "bulletinId": "29dbd7af-a948-44c4-9b36-c5a50a9b18b5",
            "prjType": "信息化软硬件采购类项目"
        },
        {
            "kbDate": "2025-08-27",
            "prjName": "慈湖景区基础设施改造提升工程（勘察设计）（重招）",
            "bulletinId": "f0a0e930-4008-4328-b1d2-95de5b33ed0c",
            "prjType": "工程类项目"
        },
        {
            "kbDate": "2025-08-27",
            "prjName": "2025年国际射联射击世界杯外聘安保服务采购",
            "bulletinId": "be7d8497-4342-4a41-8477-fdf161598c82",
            "prjType": "信息化服务类项目"
        },
        {
            "kbDate": "2025-08-27",
            "prjName": "报业集团灵桥路大楼局部装修项目工程检测服务项目",
            "bulletinId": "4f12b57c-8129-40bd-ad5d-09f7f47c292d",
            "prjType": "工程类项目"
        },
        {
            "kbDate": "2025-08-27",
            "prjName": "宁波市水务环境集团2025年计量器具数据服务(摄像采集)项目（重招）",
            "bulletinId": "d7286c15-4a06-4e30-890f-443c880d2ce4",
            "prjType": "信息化服务类项目"
        },
        {
            "kbDate": "2025-08-27",
            "prjName": "梅山铁路专用线管线迁改工程监理",
            "bulletinId": "e0038dbe-211c-473d-8a80-eaa967a3dd04",
            "prjType": "工程类项目"
        },
        {
            "kbDate": "2025-08-27",
            "prjName": "城投橙寓抖音官方账号推广",
            "bulletinId": "b5cf3c33-9190-4814-8df7-ad109e3bd9f5",
            "prjType": "信息化服务类项目"
        },
        {
            "kbDate": "2025-08-27",
            "prjName": "横港保租房宽带服务采购",
            "bulletinId": "4a36073d-4b3a-4f3e-a10e-0f2a9de84b67",
            "prjType": "信息化服务类项目"
        },
        {
            "kbDate": "2025-08-27",
            "prjName": "南苑望海酒店、招宝山饭店健身设备采购项目",
            "bulletinId": "a577e9f8-b2e4-4b48-9669-5a4f3f5124a9",
            "prjType": "工程类项目"
        },
        {
            "kbDate": "2025-08-27",
            "prjName": "慈城镇“消薄共富”租赁住房建设项目（江北区CC07-02-57c地块项目）电梯设备采购及安装项目（重发）",
            "bulletinId": "721301d0-4b2a-406a-8387-b90074823e7d",
            "prjType": "工程类项目"
        },
        {
            "kbDate": "2025-08-27",
            "prjName": "南苑望海酒店客房收视系统采购项目",
            "bulletinId": "5eabfe10-0335-4c82-a125-a51b3faecd36",
            "prjType": "信息化软硬件采购类项目"
        },
        {
            "kbDate": "2025-08-27",
            "prjName": "宁波市慈城服务区自营项目服务外包项目",
            "bulletinId": "3f82895a-5b84-41ac-b8ce-738474a530b0",
            "prjType": "信息化服务类项目"
        },
        {
            "kbDate": "2025-08-27",
            "prjName": "宁波市水务环境集团2025年镇骆路泵站格栅除污机采购项目",
            "bulletinId": "ccc767e7-9e72-4e42-81c6-c4b85e1eb5ca",
            "prjType": "信息化软硬件采购类项目"
        },
        {
            "kbDate": "2025-08-27",
            "prjName": "宁波市轨道交通运营分公司2025-2027年度职业健康危害因素检测项目",
            "bulletinId": "1b88927f-560a-4ff7-bf1a-f8be91d584e9",
            "prjType": "信息化服务类项目"
        },
        {
            "kbDate": "2025-08-27",
            "prjName": "固废处置有限公司低温余热蒸汽发电并网接入工程设备采购项目（重发）",
            "bulletinId": "e6990b7f-024f-4d87-b30f-9d184f55117d",
            "prjType": "信息化软硬件采购类项目"
        },
        {
            "kbDate": "2025-08-27",
            "prjName": "G92杭州湾地区环线高速公路宁波好思房至戚家山段工程桥梁混凝土构件低碳节地快速预制关键技术研究与应用",
            "bulletinId": "3632d134-63d1-442b-a950-b20e16ad7f08",
            "prjType": "工程类项目"
        },
        {
            "kbDate": "2025-08-27",
            "prjName": "宁波大榭开发区自来水有限公司2025年度备品材料采购项目",
            "bulletinId": "223cb8b4-ccac-434a-a7d1-02fc982d8cf9",
            "prjType": "其他项目"
        },
        {
            "kbDate": "2025-08-27",
            "prjName": "宁波洪塘220KV变电站旧址周边地块林地草地咨询项目",
            "bulletinId": "cdb46f3b-14b8-49eb-9a0f-9c25e22d2d64",
            "prjType": "其他项目"
        },
        {
            "kbDate": "2025-08-27",
            "prjName": "海曙区秀水街历史文化街区工程（海曙区秀水街HS10-03-04a、06a、06b地块）消防检测",
            "bulletinId": "60aa4bd7-6aa0-4d64-b2fd-84da6e4b6ba6",
            "prjType": "工程类项目"
        },
        {
            "kbDate": "2025-08-27",
            "prjName": "卡丁车项目进阶车采购（二次发标）",
            "bulletinId": "d858dab1-422a-4c20-93cf-af2948cc2de0",
            "prjType": "其他项目"
        },
        {
            "kbDate": "2025-08-27",
            "prjName": "2025年横街粮站改造项目工程设计",
            "bulletinId": "db956057-399e-4cb4-8eec-6db0993a2dee",
            "prjType": "工程类项目"
        },
        {
            "kbDate": "2025-08-27",
            "prjName": "宁波市海曙区孝闻街（广仁街以北地块）活力街区改造项目（测绘工程编制）",
            "bulletinId": "30f35958-2c68-471f-a417-1cb8acd67d5f",
            "prjType": "工程类项目"
        },
        {
            "kbDate": "2025-08-27",
            "prjName": "海曙区秀水街历史文化街区工程（海曙区秀水街HS10-03-04a、06a、06b地块）-逸仙楼木结构无损检测",
            "bulletinId": "58e56834-5467-418f-ae9c-f5905959e4b6",
            "prjType": "工程类项目"
        },
        {
            "kbDate": "2025-08-27",
            "prjName": "宁波市海曙区孝闻街（广仁街以北地块）活力街区改造项目（地质勘察编制）",
            "bulletinId": "deb00381-b17a-4875-a943-01c3ec4c2e9c",
            "prjType": "工程类项目"
        },
        {
            "kbDate": "2025-08-27",
            "prjName": "宁波市海曙区孝闻街（广仁街以北地块）活力街区改造项目（文物影响评估）",
            "bulletinId": "522b0a29-79d8-4c5b-9963-e89c23beb1be",
            "prjType": "工程类项目"
        },
        {
            "kbDate": "2025-08-27",
            "prjName": "海曙区秀水街历史文化街区工程（海曙区秀水街HS10-03-04a、06a、06b地块）水质检测",
            "bulletinId": "cba855a3-e965-4d87-a9d8-12c84bfa1367",
            "prjType": "工程类项目"
        }
    ]
}